{
  "resourceType": "CapabilityStatement",
  "id": "del",
  "text": {
    "status": "extensions",
    "div": "<div xmlns=\"http://www.w3.org/1999/xhtml\"><h2>CMS_Data_Element_Library_CapabilityStatement</h2><div><p>This Capability Statement defines the expected capabilities of a CMS DEL FHIR server conforming to the CMS DEL Implementation Guide.</p>\n</div><table><tr><td>Mode</td><td>SERVER</td></tr><tr><td>Description</td><td/></tr><tr><td>Transaction</td><td></td></tr><tr><td>System History</td><td></td></tr><tr><td>System Search</td><td>y</td></tr></table><table><tr><th><b>Resource Type</b></th><th><b>Profile</b></th><th><b title=\"GET a resource (read interaction)\">Read</b></th><th><b title=\"GET past versions of resources (vread interaction)\">V-Read</b></th><th><b title=\"GET all set of resources of the type (search interaction)\">Search</b></th><th><b title=\"PUT a new resource version (update interaction)\">Update</b></th><th><b title=\"POST a new resource (create interaction)\">Create</b></th><th><b title=\"GET changes to a resource (history interaction on instance)\">Updates</b></th><th><b title=\"GET changes for all resources of the type (history interaction on type)\">History</b></th></tr><tr><td>Questionnaire</td><td><a href=\"https://paciowg.github.io/del/StructureDefinition-del-StandardForm.html\">https://paciowg.github.io/del/StructureDefinition-del-StandardForm.html</a></td><td>y</td><td>y</td><td>y</td><td></td><td></td><td>y</td><td>y</td></tr></table></div>"
  },
  "url": "/CapabilityStatement-del.html",
  "version": "0.1.0",
  "name": "CMS_Data_Element_Library_CapabilityStatement",
  "title": "CMS Data Element Library CapabilityStatement",
  "status": "draft",
  "date": "2020-05-08T00:00:00+00:00",
  "contact": [
    {
      "name": "PACIO project",
      "telecom": [
        {
          "system": "url",
          "value": "http://www.hl7.org/Special/committees/patientcare/index.cfm"
        },
        {
          "system": "email",
          "value": "info@pacioproject.org"
        }
      ]
    }
  ],
  "description": "This Capability Statement defines the expected capabilities of a CMS DEL FHIR server conforming to the CMS DEL Implementation Guide.",
  "kind": "requirements",
  "fhirVersion": "4.0.1",
  "format": [
    "xml",
    "json"
  ],
  "implementationGuide": [
    "https://paciowg.github.io/del/"
  ],
  "rest": [
    {
      "mode": "server",
      "resource": [
        {
          "type": "Questionnaire",
          "profile": "https://paciowg.github.io/del/StructureDefinition-del-StandardForm.html",
          "interaction": [
            {
              "code": "read",
              "documentation": "Implemented per the specification (or Insert other doco here)"
            },
            {
              "code": "vread",
              "documentation": "Implemented per the specification (or Insert other doco here)"
            },
            {
              "code": "history-instance",
              "documentation": "Implemented per the specification (or Insert other doco here)"
            },
            {
              "code": "history-type",
              "documentation": "Implemented per the specification (or Insert other doco here)"
            },
            {
              "code": "search-type",
              "documentation": "Implemented per the specification (or Insert other doco here)"
            }
          ],
          "conditionalCreate": true,
          "conditionalUpdate": true,
          "conditionalDelete": "multiple",
          "referencePolicy": [
            "literal",
            "logical"
          ],
          "searchParam": [
            {
              "name": "date",
              "type": "date",
              "documentation": "Obtained date/time. If the obtained element is a period, a date that falls in the period"
            }
          ]
        }
      ],
      "interaction": [
        {
          "extension": [
            {
              "url": "http://hl7.org/fhir/StructureDefinition/capabilitystatement-expectation",
              "valueCode": "MAY"
            }
          ],
          "code": "batch"
        },
        {
          "extension": [
            {
              "url": "http://hl7.org/fhir/StructureDefinition/capabilitystatement-expectation",
              "valueCode": "MAY"
            }
          ],
          "code": "search-system"
        }
      ],
      "searchParam": [
        {
          "extension": [
            {
              "url": "http://hl7.org/fhir/StructureDefinition/capabilitystatement-expectation",
              "valueCode": "MAY"
            }
          ],
          "name": "_content",
          "type": "string"
        },
        {
          "extension": [
            {
              "url": "http://hl7.org/fhir/StructureDefinition/capabilitystatement-expectation",
              "valueCode": "SHALL"
            }
          ],
          "name": "_id",
          "type": "token"
        },
        {
          "extension": [
            {
              "url": "http://hl7.org/fhir/StructureDefinition/capabilitystatement-expectation",
              "valueCode": "SHALL"
            }
          ],
          "name": "_lastUpdated",
          "type": "date"
        },
        {
          "extension": [
            {
              "url": "http://hl7.org/fhir/StructureDefinition/capabilitystatement-expectation",
              "valueCode": "MAY"
            }
          ],
          "name": "_security",
          "type": "token"
        },
        {
          "extension": [
            {
              "url": "http://hl7.org/fhir/StructureDefinition/capabilitystatement-expectation",
              "valueCode": "MAY"
            }
          ],
          "name": "_text",
          "type": "string"
        },
        {
          "extension": [
            {
              "url": "http://hl7.org/fhir/StructureDefinition/capabilitystatement-expectation",
              "valueCode": "MAY"
            }
          ],
          "name": "_query",
          "type": "token"
        }
      ]
    }
  ]
}